ndmath.py
ndmath-0.0.5.dist-info/LICENSE
ndmath-0.0.5.dist-info/METADATA
ndmath-0.0.5.dist-info/WHEEL
ndmath-0.0.5.dist-info/top_level.txt
ndmath-0.0.5.dist-info/RECORD
