Metadata-Version: 2.1
Name: ndmath
Version: 0.0.5
Summary: N-dimensional complex step and finite step differentiation, and Newton's method.
Home-page: https://github.com/elcf/python-ndmath
Author: Esteban L. Castro-Feliciano
Author-email: ecastro@crown-hydro.com
License: UNKNOWN
Project-URL: Bug Tracker, https://github.com/elcf/python-ndmath/issues
Platform: UNKNOWN
Classifier: Programming Language :: Python :: 3
Classifier: License :: OSI Approved :: MIT License
Classifier: Operating System :: OS Independent
Requires-Python: >=3.6
Requires-Dist: numpy
